jsonable/__init__.py
jsonable/jsonable.py
jsonabledb-0.0.3.dist-info/LICENSE
jsonabledb-0.0.3.dist-info/METADATA
jsonabledb-0.0.3.dist-info/WHEEL
jsonabledb-0.0.3.dist-info/RECORD
